calc/__init__.py
calc/calculator.py
pankajsimplecalc-0.2.0.dist-info/METADATA
pankajsimplecalc-0.2.0.dist-info/WHEEL
pankajsimplecalc-0.2.0.dist-info/top_level.txt
pankajsimplecalc-0.2.0.dist-info/RECORD
