Metadata-Version: 2.4
Name: pankajsimplecalc
Version: 0.2.0
Summary: A simple calculator package for basic arithmetic
Author: Pankaj
Author-email: pankajshk123@gmail.com
Classifier: Programming Language :: Python :: 3
Classifier: License :: OSI Approved :: MIT License
Classifier: Operating System :: OS Independent
Requires-Python: >=3.6
Dynamic: author
Dynamic: author-email
Dynamic: classifier
Dynamic: description
Dynamic: description-content-type
Dynamic: requires-python
Dynamic: summary
